atlas_derivation/__init__.py
atlas_derivation/_version.py
atlas_derivation/components/__init__.py
atlas_derivation/components/aod_deletion_manager.py
atlas_derivation/components/did.py
atlas_derivation/components/did_collection.py
atlas_derivation/core/__init__.py
atlas_derivation/core/methods.py
atlas_derivation/utils/__init__.py
atlas_derivation/utils/common_utils.py
atlas_derivation/utils/did_utils.py
atlas_derivation/utils/system_utils.py
atlas_derivation-0.0.3.data/scripts/derivtool
atlas_derivation-0.0.3.dist-info/LICENSE
atlas_derivation-0.0.3.dist-info/METADATA
atlas_derivation-0.0.3.dist-info/WHEEL
atlas_derivation-0.0.3.dist-info/top_level.txt
atlas_derivation-0.0.3.dist-info/RECORD
