Metadata-Version: 2.1
Name: atlas-derivation
Version: 0.0.3
Summary: Package for managing derivation tasks in ATLAS
Author: Alkaid Cheng
Author-email: chi.lung.cheng@cern.ch
Classifier: Programming Language :: Python
Classifier: Programming Language :: Python :: 3
Classifier: Programming Language :: Python :: 3.8
Classifier: Programming Language :: Python :: 3.9
Classifier: Programming Language :: Python :: 3.10
Classifier: License :: OSI Approved :: Apache Software License
Classifier: Operating System :: OS Independent
Requires-Python: >=3.8
License-File: LICENSE
Requires-Dist: numpy
Requires-Dist: pandas
Requires-Dist: matplotlib
Requires-Dist: click
Requires-Dist: rucio
Requires-Dist: dateutil
